dotloop/__init__.py
dotloop/account.py
dotloop/activity.py
dotloop/authenticate.py
dotloop/bases.py
dotloop/client.py
dotloop/contact.py
dotloop/detail.py
dotloop/document.py
dotloop/folder.py
dotloop/loop.py
dotloop/loop_it.py
dotloop/loop_template.py
dotloop/participant.py
dotloop/profile.py
dotloop/task.py
dotloop/task_list.py
dotloop/blocking/__init__.py
dotloop/blocking/account.py
dotloop/blocking/activity.py
dotloop/blocking/authenticate.py
dotloop/blocking/bases.py
dotloop/blocking/client.py
dotloop/blocking/contact.py
dotloop/blocking/detail.py
dotloop/blocking/document.py
dotloop/blocking/folder.py
dotloop/blocking/loop.py
dotloop/blocking/loop_it.py
dotloop/blocking/loop_template.py
dotloop/blocking/participant.py
dotloop/blocking/profile.py
dotloop/blocking/task.py
dotloop/blocking/task_list.py
tests/__init__.py
tests/test_authentication.py
tests/test_idioms.py
dotloop_python-0.1.1.dist-info/LICENSE
dotloop_python-0.1.1.dist-info/METADATA
dotloop_python-0.1.1.dist-info/WHEEL
dotloop_python-0.1.1.dist-info/top_level.txt
dotloop_python-0.1.1.dist-info/RECORD
