Metadata-Version: 2.1
Name: dotloop-python
Version: 0.1.1
Summary: Python wrapper around the dotloop API.
Home-page: https://github.com/benr-calam/dotloop-python
Author: Ben Russell
Author-email: benr@cal-am.com
License: UNKNOWN
Project-URL: Documentation, https://github.com/benr-calam/dotloop-python
Project-URL: Source Code, https://github.com/benr-calam/dotloop-python
Keywords: dotloop,api,wrapper,requests,oauth,aiohttp
Platform: UNKNOWN
Classifier: Programming Language :: Python :: 3
Classifier: License :: OSI Approved :: MIT License
Classifier: Operating System :: OS Independent
Requires-Python: >=3.8
Requires-Dist: requests
Requires-Dist: aiohttp
